{
  "Audio": [
    {
      "name": "Audacity",
      "url": "http://audacityteam.org/",
      "description": "Free, open source, cross-platform software for recording and editing sounds. [![Open-Source Software][OSS Icon]](https://github.com/audacity/audacity)",
      "cate": "Audio"
    },
    {
      "name": "Cog",
      "url": "http://cogx.org/",
      "description": "A free open source audio player for OS X. [![Open-Source Software][OSS Icon]](https://bitbucket.org/mamburu/cog/)",
      "cate": "Audio"
    },
    {
      "name": "VOX Player",
      "url": "https://coppertino.com/vox/mac",
      "description": "Play numerous lossy and lossless audio formats.",
      "cate": "Audio"
    },
    {
      "name": "XLD",
      "url": "http://tmkk.undo.jp/xld/index_e.html",
      "description": "Rip/Decode/convert/play various \"lossless\" audio files. [![Open-Source Software][OSS Icon]](https://code.google.com/p/xld/source/checkout)",
      "cate": "Audio"
    }
  ],
  "Bookmark Utilities": [
    {
      "name": "ReadKit",
      "url": "http://readkitapp.com/",
      "description": "Have all your Instapaper, Pocket, etc. feeds in one place even when you're offline.",
      "cate": "Bookmark Utilities"
    },
    {
      "name": "Spillo",
      "url": "http://bananafishsoftware.com/products/spillo/",
      "description": "Powerful, beautiful and fast Pinboard client.",
      "cate": "Bookmark Utilities"
    }
  ],
  "Chat Clients": [
    {
      "name": "ChitChat",
      "url": "https://github.com/stonesam92/ChitChat",
      "description": "A native Mac app wrapper for WhatsApp Web. [![Open-Source Software][OSS Icon]](https://github.com/stonesam92/ChitChat)",
      "cate": "Chat Clients"
    },
    {
      "name": "LimeChat",
      "url": "http://limechat.net/mac/",
      "description": "Instant messaging application. [![Open-Source Software][OSS Icon]](https://github.com/psychs/limechat)",
      "cate": "Chat Clients"
    },
    {
      "name": "Messenger for Desktop",
      "url": "http://messengerfordesktop.com/",
      "description": "An app for Facebook messenger. [![Open-Source Software][OSS Icon]](https://github.com/Aluxian/Facebook-Messenger-Desktop)",
      "cate": "Chat Clients"
    },
    {
      "name": "Profanity",
      "url": "http://www.profanity.im",
      "description": "A terminal XMPP client. [![Open-Source Software][OSS Icon]](https://github.com/boothj5/profanity)",
      "cate": "Chat Clients"
    },
    {
      "name": "Slack",
      "url": "https://itunes.apple.com/in/app/slack/id803453959",
      "description": "A messaging app for teams.",
      "cate": "Chat Clients"
    },
    {
      "name": "Telegram",
      "url": "https://itunes.apple.com/us/app/telegram/id747648890?mt=12",
      "description": "A messaging app with a focus on speed and security, it’s super fast, simple and free.",
      "cate": "Chat Clients"
    },
    {
      "name": "Textual 5",
      "url": "https://www.codeux.com/textual/",
      "description": "An Internet Relay Chat (IRC) client. [![Open-Source Software][OSS Icon]](https://github.com/Codeux-Software/Textual)",
      "cate": "Chat Clients"
    },
    {
      "name": "WeeChat",
      "url": "https://weechat.org",
      "description": "A terminal IRC client. [![Open-Source Software][OSS Icon]](https://github.com/weechat/weechat)",
      "cate": "Chat Clients"
    }
  ],
  "Data Recovery": [
    {
      "name": "Data Rescue",
      "url": "https://www.prosofteng.com/datarescue4/",
      "description": "Comprehensive and professional data recovery for a multitude of scenarios.",
      "cate": "Data Recovery"
    },
    {
      "name": "DiskWarrior",
      "url": "http://www.alsoft.com/DiskWarrior/",
      "description": "Recover from filesystem corruptions when Disk Utility is out of options.",
      "cate": "Data Recovery"
    }
  ],
  "Developers": [
    {
      "name": "Base 2",
      "url": "http://menial.co.uk/base/",
      "description": "A GUI for managing SQLite databases.",
      "cate": "Developers"
    },
    {
      "name": "Cakebrew",
      "url": "https://www.cakebrew.com/",
      "description": "The Homebrew GUI App. [![Open-Source Software][OSS Icon]](https://github.com/brunophilipe/Cakebrew)",
      "cate": "Developers"
    },
    {
      "name": "Charles",
      "url": "http://www.charlesproxy.com",
      "description": "Charles is a Proxy that allow you to view all of the HTTP and HTTPS traffic.",
      "cate": "Developers"
    },
    {
      "name": "Dash",
      "url": "https://kapeli.com/dash",
      "description": "An API Documentation Browser and Code Snippet Manager.",
      "cate": "Developers"
    },
    {
      "name": "Gas Mask",
      "url": "https://github.com/2ndalpha/gasmask",
      "description": "A simple hosts file manager which allows editing of host files and switching between them. [![Open-Source Software][OSS Icon]](https://github.com/2ndalpha/gasmask)",
      "cate": "Developers"
    },
    {
      "name": "GitHub Desktop",
      "url": "https://mac.github.com/",
      "description": "A GUI for using GitHub.",
      "cate": "Developers"
    },
    {
      "name": "GitUp",
      "url": "http://gitup.co/",
      "description": "A simple but powerful Git OS X app. [![Open-Source Software][OSS Icon]](https://github.com/git-up/GitUp)",
      "cate": "Developers"
    },
    {
      "name": "Hosts",
      "url": "https://github.com/specialunderwear/Hosts.prefpane",
      "description": "Edit hosts file. [![Open-Source Software][OSS Icon]](https://github.com/specialunderwear/Hosts.prefpane)",
      "cate": "Developers"
    },
    {
      "name": "ImageAlpha",
      "url": "http://pngmini.com/",
      "description": "Apply lossy compression on PNG files with or without transparency for more efficient files. [![Open-Source Software][OSS Icon]](https://github.com/pornel/ImageAlpha)",
      "cate": "Developers"
    },
    {
      "name": "ImageOptim",
      "url": "https://imageoptim.com/",
      "description": "Makes images take up less disk space and load faster. [![Open-Source Software][OSS Icon]](https://github.com/pornel/ImageOptim)",
      "cate": "Developers"
    },
    {
      "name": "Insomnia",
      "url": "http://insomnia.rest",
      "description": "A modern REST client with an beautiful interface.",
      "cate": "Developers"
    },
    {
      "name": "Integrity",
      "url": "http://peacockmedia.software/mac/integrity/free.html",
      "description": "Easily find your website's broken links.",
      "cate": "Developers"
    },
    {
      "name": "Paw",
      "url": "https://luckymarmot.com/paw",
      "description": "The ultimate REST client.",
      "cate": "Developers"
    },
    {
      "name": "PSequel",
      "url": "http://www.psequel.com/",
      "description": "A PostgreSQL GUI tool.",
      "cate": "Developers"
    },
    {
      "name": "Sequel Pro",
      "url": "http://www.sequelpro.com/",
      "description": "A MySQL database manager. [![Open-Source Software][OSS Icon]](https://github.com/sequelpro/sequelpro)",
      "cate": "Developers"
    },
    {
      "name": "Sip",
      "url": "http://theolabrothers.com/",
      "description": "A simple color picker for developers.",
      "cate": "Developers"
    },
    {
      "name": "SourceTree",
      "url": "https://www.sourcetreeapp.com/",
      "description": "A free Git & Mercurial client.",
      "cate": "Developers"
    },
    {
      "name": "StarUML",
      "url": "http://staruml.io",
      "description": "A sophisticated software modeler.",
      "cate": "Developers"
    },
    {
      "name": "Tower",
      "url": "http://www.git-tower.com/",
      "description": "The most powerful Git client.",
      "cate": "Developers"
    },
    {
      "name": "Unused",
      "url": "https://jeffhodnett.github.io/Unused/",
      "description": "An app for checking Xcode projects for unused resources. [![Open-Source Software][OSS Icon]](https://github.com/jeffhodnett/Unused)",
      "cate": "Developers"
    },
    {
      "name": "WWDC",
      "url": "https://github.com/insidegui/WWDC",
      "description": "The WWDC app. [![Open-Source Software][OSS Icon]](https://github.com/insidegui/WWDC)",
      "cate": "Developers"
    },
    {
      "name": "Zsh",
      "url": "http://www.zsh.org/",
      "description": " A powerful command line shell. [![Open-Source Software][OSS Icon]](http://sourceforge.net/p/zsh/code/ci/master/tree/)",
      "cate": "Developers"
    }
  ],
  "E-Book Utilities": [
    {
      "name": "Calibre",
      "url": "http://calibre-ebook.com/",
      "description": "Incredibly ugly but powerful software for ebook management and conversion. [![Open-Source Software][OSS Icon]](https://github.com/kovidgoyal/calibre)",
      "cate": "E-Book Utilities"
    },
    {
      "name": "Kindle App",
      "url": "http://www.amazon.com/gp/help/customer/display.html?nodeId=201246110",
      "description": "Amazon Kindle App for OS X.",
      "cate": "E-Book Utilities"
    },
    {
      "name": "Kitabu",
      "url": "https://www.kitabu.me/",
      "description": "Desktop ePub ebook reader.",
      "cate": "E-Book Utilities"
    }
  ],
  "Editors": [
    {
      "name": "Atom",
      "url": "https://atom.io/",
      "description": "The hackable text editor. [![Open-Source Software][OSS Icon]](https://github.com/atom/atom)",
      "cate": "Editors"
    },
    {
      "name": "Brackets",
      "url": "http://brackets.io/",
      "description": "A modern text editor that understands web design. [![Open-Source Software][OSS Icon]](https://github.com/adobe/brackets)",
      "cate": "Editors"
    },
    {
      "name": "Emacs",
      "url": "https://github.com/railwaycat/mirror-emacs-mac",
      "description": "Port of Emacs to work as an OS X app. [![Open-Source Software][OSS Icon]](https://github.com/railwaycat/mirror-emacs-mac)",
      "cate": "Editors"
    },
    {
      "name": "Light Table",
      "url": "http://lighttable.com/",
      "description": "A customizable editor with REPL support for Clojure, JavaScript, Python and others. [![Open-Source Software][OSS Icon]](https://github.com/LightTable/LightTable)",
      "cate": "Editors"
    },
    {
      "name": "MacVim",
      "url": "https://github.com/macvim-dev/macvim",
      "description": "Vim, the text editor. [![Open-Source Software][OSS Icon]](https://github.com/macvim-dev/macvim)",
      "cate": "Editors"
    },
    {
      "name": "Sublime Text 3",
      "url": "http://www.sublimetext.com/",
      "description": "The sophisticated text editor.",
      "cate": "Editors"
    },
    {
      "name": "TextMate",
      "url": "https://macromates.com/",
      "description": "A graphical text editor. [![Open-Source Software][OSS Icon]](https://github.com/textmate/textmate)",
      "cate": "Editors"
    },
    {
      "name": "VimR",
      "url": "http://vimr.org",
      "description": "Vim, refined. [![Open-Source Software][OSS Icon]](https://github.com/qvacua/vimr)",
      "cate": "Editors"
    },
    {
      "name": "Visual Studio Code",
      "url": "https://code.visualstudio.com/",
      "description": "Build and debug modern web and cloud applications.",
      "cate": "Editors"
    }
  ],
  "Email Utilities": [
    {
      "name": "Airmail",
      "url": "http://airmailapp.com/",
      "description": "Lightning fast email client designed for El Capitan, and a free Beta.",
      "cate": "Email Utilities"
    },
    {
      "name": "MailMate",
      "url": "http://freron.com/",
      "description": "Advanced IMAP email client, featuring extensive keyboard control and Markdown support.",
      "cate": "Email Utilities"
    }
  ],
  "Finder": [
    {
      "name": "ForkLift",
      "url": "https://itunes.apple.com/us/app/forklift-file-manager-ftp/id412448059",
      "description": "File Manager and FTP/SFTP/WebDAV/Amazon S3 client.",
      "cate": "Finder"
    },
    {
      "name": "Path Finder",
      "url": "http://www.cocoatech.com/pathfinder/",
      "description": "A powerful dual-pane browser alternative to Finder.",
      "cate": "Finder"
    },
    {
      "name": "TotalFinder",
      "url": "http://totalfinder.binaryage.com/",
      "description": "A powerful alternative to Finder.",
      "cate": "Finder"
    },
    {
      "name": "XtraFinder",
      "url": "https://www.trankynam.com/xtrafinder/",
      "description": "Adds useful features to Finder.",
      "cate": "Finder"
    }
  ],
  "Games": [
    {
      "name": "Battle for Wesnoth",
      "url": "http://www.wesnoth.org/",
      "description": "Turn-based tactical strategy game, featuring both single-player and online multiplayer combat. [![Open-Source Software][OSS Icon]](https://github.com/wesnoth)",
      "cate": "Games"
    },
    {
      "name": "Boxer",
      "url": "http://boxerapp.com/",
      "description": "The DOS game emulator that’s fit for your Mac. [![Open-Source Software][OSS Icon]](https://github.com/alunbestor/Boxer)",
      "cate": "Games"
    },
    {
      "name": "OpenEmu",
      "url": "http://openemu.org/",
      "description": "Multiple Video Game System. [![Open-Source Software][OSS Icon]](https://github.com/OpenEmu/OpenEmu)",
      "cate": "Games"
    },
    {
      "name": "Screentendo",
      "url": "http://aaronrandall.com/blog/screentendo/",
      "description": "Turn your screen into a playable level of Mario. [![Open-Source Software][OSS Icon]](https://github.com/AaronRandall/Screentendo)",
      "cate": "Games"
    },
    {
      "name": "Stockfish",
      "url": "http://stockfishchess.org/mac/",
      "description": "Beautiful, powerful chess application. [![Open-Source Software][OSS Icon]](https://github.com/daylen/stockfish-mac)",
      "cate": "Games"
    }
  ],
  "Graphics": [
    {
      "name": "Acorn",
      "url": "https://secure.flyingmeat.com/acorn/",
      "description": "A very Mac-like image editor with a comprehensive feature set.",
      "cate": "Graphics"
    },
    {
      "name": "OmniGraffle",
      "url": "https://www.omnigroup.com/omnigraffle",
      "description": "An app for creating precise, beautiful graphics.",
      "cate": "Graphics"
    },
    {
      "name": "Pixelmator",
      "url": "http://www.pixelmator.com/",
      "description": "Powerful image editor, possible Photoshop alternative.",
      "cate": "Graphics"
    },
    {
      "name": "Sketch",
      "url": "http://bohemiancoding.com/sketch/",
      "description": "Hybrid vector/bitmap layout application, especially useful for UI, web and mobile design.",
      "cate": "Graphics"
    },
    {
      "name": "xScope",
      "url": "http://xscopeapp.com/",
      "description": "Tools for measuring, inspecting and testing on-screen graphics and layouts.",
      "cate": "Graphics"
    }
  ],
  "Productivity": [
    {
      "name": "Alfred",
      "url": "http://www.alfredapp.com/",
      "description": "Boosts your efficiency and productivity.",
      "cate": "Productivity"
    },
    {
      "name": "Amethyst",
      "url": "http://ianyh.com/amethyst/",
      "description": "Window manager (automatically keep windows sized in grids). [![Open-Source Software][OSS Icon]](https://github.com/ianyh/Amethyst)",
      "cate": "Productivity"
    },
    {
      "name": "BetterTouchTool",
      "url": "http://www.bettertouchtool.net/",
      "description": "Configure gestures for mouse and actions for keyboard shortcuts.",
      "cate": "Productivity"
    },
    {
      "name": "ClipMenu",
      "url": "http://www.clipmenu.com/",
      "description": "ClipBoard History Manager.",
      "cate": "Productivity"
    },
    {
      "name": "CloudClip",
      "url": "http://www.thinkbitz.com/cloudclip/",
      "description": "Sync your clipboard between your Mac and your iOS devices.",
      "cate": "Productivity"
    },
    {
      "name": "Divvy Window Manager",
      "url": "http://mizage.com/divvy/",
      "description": "Window management for tiling your windows.",
      "cate": "Productivity"
    },
    {
      "name": "f.lux",
      "url": "http://stereopsis.com/flux/",
      "description": "Automatically adjust your computer screen to match lighting.",
      "cate": "Productivity"
    },
    {
      "name": "Hazel",
      "url": "https://www.noodlesoft.com/hazel.php",
      "description": "Create rules to automatically keep your files organized.",
      "cate": "Productivity"
    },
    {
      "name": "HyperDock",
      "url": "https://bahoom.com/hyperdock/",
      "description": "Select individual application window.",
      "cate": "Productivity"
    },
    {
      "name": "Karabiner",
      "url": "https://pqrs.org/osx/karabiner/",
      "description": "A powerful keyboard customizer. [![Open-Source Software][OSS Icon]](https://github.com/tekezo/Karabiner)",
      "cate": "Productivity"
    },
    {
      "name": "LaunchBar",
      "url": "https://www.obdev.at/products/launchbar/",
      "description": "Start applications, navigate folders, manipulate files, control your Mac and much more just by using the keyboard.",
      "cate": "Productivity"
    },
    {
      "name": "OmniFocus",
      "url": "https://www.omnigroup.com/omnifocus",
      "description": "An incredible task management platform for Mac, iPad, and iPhone.",
      "cate": "Productivity"
    },
    {
      "name": "Paste",
      "url": "http://pasteapp.me",
      "description": "The new way to copy & paste for Mac.",
      "cate": "Productivity"
    },
    {
      "name": "PopClip",
      "url": "http://pilotmoon.com/popclip/",
      "description": "Instantly copy & paste, access actions like search, spelling, dictionary and more.",
      "cate": "Productivity"
    },
    {
      "name": "Quicksilver",
      "url": "http://qsapp.com/",
      "description": "Control your Mac quickly and elegantly. [![Open-Source Software][OSS Icon]](https://github.com/quicksilver/Quicksilver)",
      "cate": "Productivity"
    },
    {
      "name": "SelfControl",
      "url": "https://selfcontrolapp.com/",
      "description": "Block access to distracting websites. [![Open-Source Software][OSS Icon]](https://github.com/SelfControlApp/selfcontrol/)",
      "cate": "Productivity"
    },
    {
      "name": "Spectacle",
      "url": "http://spectacleapp.com/",
      "description": "Easily organize windows without using a mouse. [![Open-Source Software][OSS Icon]](https://github.com/eczarny/spectacle)",
      "cate": "Productivity"
    },
    {
      "name": "TextExpander",
      "url": "https://smilesoftware.com/TextExpander/index.html",
      "description": "Create custom keyboard shortcuts for frequently-used text and pictures.",
      "cate": "Productivity"
    },
    {
      "name": "Todoist",
      "url": "https://todoist.com/mac",
      "description": "Cross-platform to-do manager with mobile apps, great UI and has some optional premium features.",
      "cate": "Productivity"
    },
    {
      "name": "Zooom/2",
      "url": "http://coderage-software.com/zooom/index_green/index.html",
      "description": "Mac window management.",
      "cate": "Productivity"
    }
  ],
  "Sharing Files": [
    {
      "name": "BitTorrent Sync",
      "url": "https://www.getsync.com/",
      "description": "Multi platform sync tool using BitTorrent protocol.",
      "cate": "Sharing Files"
    },
    {
      "name": "CloudApp",
      "url": "https://www.getcloudapp.com/",
      "description": "Capture and share files and screenshots instantly.",
      "cate": "Sharing Files"
    },
    {
      "name": "mac2imgur",
      "url": "https://github.com/mileswd/mac2imgur",
      "description": "Upload images and screenshots to Imgur. [![Open-Source Software][OSS Icon]](https://github.com/mileswd/mac2imgur)",
      "cate": "Sharing Files"
    }
  ],
  "Terminal": [
    {
      "name": "iTerm 2",
      "url": "https://www.iterm2.com/",
      "description": "A terminal emulator. [![Open-Source Software][OSS Icon]](https://github.com/gnachman/iTerm2)",
      "cate": "Terminal"
    },
    {
      "name": "TotalTerminal",
      "url": "http://totalterminal.binaryage.com/",
      "description": "A system-wide terminal available on a hot-key.",
      "cate": "Terminal"
    }
  ],
  "Utilities": [
    {
      "name": "1Password",
      "url": "https://itunes.apple.com/in/app/1password-password-manager/id443987910?mt=12",
      "description": "Password Manager and Secure Wallet.",
      "cate": "Utilities"
    },
    {
      "name": "Amphetamine",
      "url": "https://itunes.apple.com/app/amphetamine/id937984704",
      "description": "Prevents OS X from automatically going to sleep, with lots of configurations.",
      "cate": "Utilities"
    },
    {
      "name": "AnyBar",
      "url": "https://github.com/tonsky/AnyBar",
      "description": "A menubar status indicator. [![Open-Source Software][OSS Icon]](https://github.com/tonsky/AnyBar)",
      "cate": "Utilities"
    },
    {
      "name": "AppCleaner",
      "url": "http://www.freemacsoft.net/appcleaner/",
      "description": "Uninstall your apps easily.",
      "cate": "Utilities"
    },
    {
      "name": "Arthur",
      "url": "http://arthur-osx.com/",
      "description": "Safely optimize some of your Mac's hidden settings.",
      "cate": "Utilities"
    },
    {
      "name": "Bartender",
      "url": "http://www.macbartender.com/",
      "description": "Organize your menu bar apps.",
      "cate": "Utilities"
    },
    {
      "name": "BeardedSpice",
      "url": "http://beardedspice.com/",
      "description": "Control web based media players with the media keys found on Mac keyboards. [![Open-Source Software][OSS Icon]](https://github.com/beardedspice/beardedspice)",
      "cate": "Utilities"
    },
    {
      "name": "BetterZip",
      "url": "http://macitbetter.com/",
      "description": "A very capable and full-featured archive manager.",
      "cate": "Utilities"
    },
    {
      "name": "BitBar",
      "url": "https://github.com/matryer/bitbar",
      "description": "Display output of any script to the menu bar. [![Open-Source Software][OSS Icon]](https://github.com/matryer/bitbar)",
      "cate": "Utilities"
    },
    {
      "name": "ControlPlane",
      "url": "http://www.controlplaneapp.com/",
      "description": "Automate running tasks based on where you are or what you do. [![Open-Source Software][OSS Icon]](https://github.com/dustinrue/ControlPlane)",
      "cate": "Utilities"
    },
    {
      "name": "DaisyDisk",
      "url": "http://www.daisydiskapp.com/",
      "description": "Analyze disk usage and free up disk space.",
      "cate": "Utilities"
    },
    {
      "name": "EtreCheck",
      "url": "http://www.etresoft.com/etrecheck",
      "description": "Output system information and configuration to get more informed help from Apple support professionals. [![Open-Source Software][OSS Icon]](https://github.com/etresoft/EtreCheck)",
      "cate": "Utilities"
    },
    {
      "name": "Finicky",
      "url": "https://johnste.github.io/finicky/",
      "description": "App that allows you to set rules that decide which browser is opened for every link. [![Open-Source Software][OSS Icon]](https://github.com/johnste/finicky)",
      "cate": "Utilities"
    },
    {
      "name": "Fluid",
      "url": "http://fluidapp.com/",
      "description": "Turn web applications into Mac applications.",
      "cate": "Utilities"
    },
    {
      "name": "Helium",
      "url": "http://heliumfloats.com/",
      "description": "A floating browser window that allows you to watch media while you work. [![Open-Source Software][OSS Icon]](https://github.com/JadenGeller/Helium)",
      "cate": "Utilities"
    },
    {
      "name": "InsomniaX",
      "url": "http://semaja2.net/projects/insomniaxinfo/",
      "description": "Prevents OS X from automatically going to sleep (on lid closing or idle timeout).",
      "cate": "Utilities"
    },
    {
      "name": "iStat Menus",
      "url": "https://bjango.com/mac/istatmenus/",
      "description": "An advanced system monitor for your menubar.",
      "cate": "Utilities"
    },
    {
      "name": "Kawa",
      "url": "https://github.com/noraesae/kawa",
      "description": "A better input source switcher with shortcuts. [![Open-Source Software][OSS Icon]](https://github.com/noraesae/kawa)",
      "cate": "Utilities"
    },
    {
      "name": "Keka",
      "url": "http://www.kekaosx.com/en/",
      "description": "Compress to and extract from many archive file formats. [![Open-Source Software][OSS Icon]](http://sourceforge.net/projects/keka/files/)",
      "cate": "Utilities"
    },
    {
      "name": "Knock",
      "url": "http://www.knocktounlock.com",
      "description": "Unlock your Mac quickly and securely. Now with Apple Watch.",
      "cate": "Utilities"
    },
    {
      "name": "Loading",
      "url": "http://bonzaiapps.com",
      "description": "See when apps are using your network in your Mac menubar. [![Open-Source Software][OSS Icon]](https://github.com/BonzaiThePenguin/Loading/)",
      "cate": "Utilities"
    },
    {
      "name": "MacDown",
      "url": "http://macdown.uranusjr.com/",
      "description": "Markdown editor. [![Open-Source Software][OSS Icon]](https://github.com/uranusjr/macdown)",
      "cate": "Utilities"
    },
    {
      "name": "Mackup",
      "url": "https://github.com/lra/mackup",
      "description": "Keep your application settings in sync. [![Open-Source Software][OSS Icon]](https://github.com/lra/mackup)",
      "cate": "Utilities"
    },
    {
      "name": "MacPass",
      "url": "http://mstarke.github.io/MacPass",
      "description": "Password Manager. [![Open-Source Software][OSS Icon]](https://github.com/mstarke/MacPass)",
      "cate": "Utilities"
    },
    {
      "name": "Media Converter",
      "url": "http://media-converter.sourceforge.net/",
      "description": "Simple (drag and drop) but advanced media conversion. [![Open-Source Software][OSS Icon]](http://sourceforge.net/p/media-converter/code/HEAD/tree/)",
      "cate": "Utilities"
    },
    {
      "name": "Menubar Colors",
      "url": "https://github.com/nvzqz/Menubar-Colors",
      "description": "Convenient access to the system color panel. [![Open-Source Software][OSS Icon]](https://github.com/nvzqz/Menubar-Colors)",
      "cate": "Utilities"
    },
    {
      "name": "Monodraw",
      "url": "http://monodraw.helftone.com/",
      "description": "A powerful ASCII art editor.",
      "cate": "Utilities"
    },
    {
      "name": "Notational Velocity",
      "url": "http://notational.net/",
      "description": "Store, retrieve and sync notes within a minimal GUI. [![Open-Source Software][OSS Icon]](https://github.com/scrod/nv/)",
      "cate": "Utilities"
    },
    {
      "name": "Numi",
      "url": "http://numi.io/",
      "description": "Beautiful calculator app.",
      "cate": "Utilities"
    },
    {
      "name": "Site Sucker",
      "url": "http://ricks-apps.com/osx/sitesucker/",
      "description": "Automatically download websites from the Internet.",
      "cate": "Utilities"
    },
    {
      "name": "ShiftIt",
      "url": "https://github.com/fikovnik/ShiftIt",
      "description": "Managing windows size and position. [![Open-Source Software][OSS Icon]](https://github.com/fikovnik/ShiftIt)",
      "cate": "Utilities"
    },
    {
      "name": "Subtitles",
      "url": "http://subtitlesapp.com/",
      "description": "Automatically downloads subtitles for your movies and TV shows.",
      "cate": "Utilities"
    },
    {
      "name": "TeamViewer",
      "url": "http://www.teamviewer.com/en/index.aspx",
      "description": "Remotely control another computer.",
      "cate": "Utilities"
    },
    {
      "name": "TextBar",
      "url": "http://www.richsomerfield.com/apps/",
      "description": "TextBar is a tiny but powerful app that lets you add any text to your MenuBar.",
      "cate": "Utilities"
    },
    {
      "name": "Typora",
      "url": "http://www.typora.io/",
      "description": "Another minial Markdown editor.",
      "cate": "Utilities"
    },
    {
      "name": "Übersicht",
      "url": "http://tracesof.net/uebersicht/",
      "description": "Run system commands and display their output on your desktop as widgets. [![Open-Source Software][OSS Icon]](https://github.com/felixhageloh/uebersicht)",
      "cate": "Utilities"
    },
    {
      "name": "The Unarchiver",
      "url": "http://unarchiver.c3.cx/unarchiver",
      "description": "Unarchive many different kinds of archive files. [![Open-Source Software][OSS Icon]](https://bitbucket.org/WAHa_06x36/theunarchiver)",
      "cate": "Utilities"
    }
  ],
  "Video": [
    {
      "name": "HandBrake",
      "url": "http://handbrake.fr/",
      "description": "High performance video encoding and conversion tools with a nice GUI. [![Open-Source Software][OSS Icon]](https://github.com/HandBrake/HandBrake)",
      "cate": "Video"
    },
    {
      "name": "MPlayerX",
      "url": "http://mplayerx.org",
      "description": "Media player. [![Open-Source Software][OSS Icon]](https://github.com/niltsh/MPlayerX)",
      "cate": "Video"
    },
    {
      "name": "mpv",
      "url": "http://mpv.io/",
      "description": "Media player. [![Open-Source Software][OSS Icon]](https://github.com/mpv-player/mpv)",
      "cate": "Video"
    },
    {
      "name": "ScreenFlow",
      "url": "http://www.telestream.net/screenflow/",
      "description": "Screencasting and video editing software.",
      "cate": "Video"
    },
    {
      "name": "Subler",
      "url": "https://bitbucket.org/galad87/subler/wiki/Home",
      "description": "Mux and tag MP4 files. [![Open-Source Software][OSS Icon]](https://bitbucket.org/galad87/subler/wiki/Home)",
      "cate": "Video"
    }
  ],
  "Others": [
    {
      "name": "Aerial",
      "url": "https://github.com/JohnCoates/Aerial",
      "description": "Apple TV Aerial Screensaver for Mac. [![Open-Source Software][OSS Icon]](https://github.com/JohnCoates/Aerial)",
      "cate": "Others"
    },
    {
      "name": "Catch",
      "url": "http://www.giorgiocalderolla.com/index.html#catch",
      "description": "The easiest way to use ShowRSS. [![Open-Source Software][OSS Icon]](https://github.com/mipstian/catch/)",
      "cate": "Others"
    },
    {
      "name": "gInbox",
      "url": "https://github.com/chenasraf/gInbox",
      "description": "gInbox is a wrapper made for Mac around Inbox by Gmail. [![Open-Source Software][OSS Icon]](https://github.com/chenasraf/gInbox)",
      "cate": "Others"
    },
    {
      "name": "Hacky",
      "url": "http://www.hackyapp.com/",
      "description": "Hacky provides browsing Hacker News in a clean and minimalistic way. [![Open-Source Software][OSS Icon]](https://github.com/eliaskg/Hacky)",
      "cate": "Others"
    },
    {
      "name": "PopKey",
      "url": "http://popkey.co/send-gifs",
      "description": " Allows easy access to animated GIFs from the Mac menu bar.",
      "cate": "Others"
    },
    {
      "name": "Sonora",
      "url": "http://getsonora.com/",
      "description": " A minimal, beautifully designed music player. [![Open-Source Software][OSS Icon]](https://github.com/sonoramac/Sonora)",
      "cate": "Others"
    },
    {
      "name": "SoundCleod",
      "url": "http://soundcleod.com/",
      "description": "A browser for SoundCloud. [![Open-Source Software][OSS Icon]](https://github.com/salomvary/soundcleod)",
      "cate": "Others"
    },
    {
      "name": "Transmit",
      "url": "https://panic.com/transmit/",
      "description": "A FTP client.",
      "cate": "Others"
    },
    {
      "name": "Vienna",
      "url": "http://www.vienna-rss.org/",
      "description": "RSS/Atom newsreader. [![Open-Source Software][OSS Icon]](https://github.com/ViennaRSS/vienna-rss)",
      "cate": "Others"
    },
    {
      "name": "Awesome OS X Command Line",
      "url": "https://github.com/herrbischoff/awesome-osx-command-line",
      "description": "Use your OS X terminal shell to do awesome things.",
      "cate": "Others"
    },
    {
      "name": "Mac OS X Manual Pages",
      "url": "https://developer.apple.com/library/mac/documentation/Darwin/Reference/ManPages/",
      "description": "Apple's official man page reference which lists all general commands in Section 1.",
      "cate": "Others"
    },
    {
      "name": "Glances",
      "url": "https://github.com/nicolargo/glances",
      "description": "System monitoring tool that runs in terminal. [![Open-Source Software][OSS Icon]](https://github.com/nicolargo/glances)",
      "cate": "Others"
    }
  ],
  "OS X 10.11 El Capitan Setup\n\n* https://gist.github.com/saetia/1623487\n\n\n## Security\n\n* [GPG Suite](https://gpgtools.org/)": [
    {
      "name": "GPG Suite",
      "url": "https://gpgtools.org/",
      "description": "Full GPG toolkit with easy to understand GUI applications and Mail.app plugin.",
      "cate": "OS X 10.11 El Capitan Setup\n\n* https://gist.github.com/saetia/1623487\n\n\n## Security\n\n* [GPG Suite](https://gpgtools.org/)"
    },
    {
      "name": "macchanger",
      "url": "https://acrogenesis.com/macchanger/",
      "description": "Easily change your MAC Address [![Open-Source Software][OSS Icon]](https://github.com/acrogenesis/macchanger)",
      "cate": "OS X 10.11 El Capitan Setup\n\n* https://gist.github.com/saetia/1623487\n\n\n## Security\n\n* [GPG Suite](https://gpgtools.org/)"
    },
    {
      "name": "MIDAS",
      "url": "https://github.com/etsy/MIDAS",
      "description": "Intrusion Detection Analysis System. [![Open-Source Software][OSS Icon]](https://github.com/etsy/MIDAS)",
      "cate": "OS X 10.11 El Capitan Setup\n\n* https://gist.github.com/saetia/1623487\n\n\n## Security\n\n* [GPG Suite](https://gpgtools.org/)"
    },
    {
      "name": "OSXAuditor",
      "url": "https://github.com/jipegit/OSXAuditor",
      "description": "A free computer forensics tool. [![Open-Source Software][OSS Icon]](https://github.com/jipegit/OSXAuditor)",
      "cate": "OS X 10.11 El Capitan Setup\n\n* https://gist.github.com/saetia/1623487\n\n\n## Security\n\n* [GPG Suite](https://gpgtools.org/)"
    },
    {
      "name": "santa",
      "url": "https://github.com/google/santa",
      "description": "A binary whitelisting/blacklisting system. [![Open-Source Software][OSS Icon]](https://github.com/google/santa)",
      "cate": "OS X 10.11 El Capitan Setup\n\n* https://gist.github.com/saetia/1623487\n\n\n## Security\n\n* [GPG Suite](https://gpgtools.org/)"
    },
    {
      "name": "Viscosity",
      "url": "https://www.sparklabs.com/viscosity/",
      "description": "Fully-featured OpenVPN client, ready for enterprise deployment.",
      "cate": "OS X 10.11 El Capitan Setup\n\n* https://gist.github.com/saetia/1623487\n\n\n## Security\n\n* [GPG Suite](https://gpgtools.org/)"
    }
  ]
}
